{
	"format_version": "1.12.0",
	"minecraft:geometry": [
		{
			"description": {
				"identifier": "geometry.nature_guardian",
				"texture_width": 128,
				"texture_height": 128,
				"visible_bounds_width": 4,
				"visible_bounds_height": 5.5,
				"visible_bounds_offset": [0, 2.25, 0]
			},
			"bones": [
				{
					"name": "root",
					"pivot": [0, 0, 0]
				},
				{
					"name": "body",
					"parent": "root",
					"pivot": [0, 34, 0]
				},
				{
					"name": "body5",
					"parent": "body",
					"pivot": [0, 22, 0],
					"cubes": [
						{"origin": [-4, 14, -4], "size": [8, 8, 8], "uv": [44, 0]}
					]
				},
				{
					"name": "cores",
					"parent": "body5",
					"pivot": [0, 10, 0]
				},
				{
					"name": "core1",
					"parent": "cores",
					"pivot": [0, 10, 0],
					"cubes": [
						{"origin": [-2, 8, -2], "size": [4, 4, 4], "uv": [60, 45]}
					]
				},
				{
					"name": "core2",
					"parent": "cores",
					"pivot": [0, 10, 0],
					"cubes": [
						{"origin": [-2, 8, -2], "size": [4, 4, 4], "uv": [60, 45]}
					]
				},
				{
					"name": "core3",
					"parent": "cores",
					"pivot": [0, 10, 0],
					"cubes": [
						{"origin": [-2, 8, -2], "size": [4, 4, 4], "uv": [60, 45]}
					]
				},
				{
					"name": "rods",
					"parent": "body5",
					"pivot": [0, 14, 0]
				},
				{
					"name": "rod1",
					"parent": "rods",
					"pivot": [0, 14, 0],
					"cubes": [
						{"origin": [-0.5, 0, -4], "size": [1, 14, 1], "uv": [78, 53]}
					]
				},
				{
					"name": "rod2",
					"parent": "rods",
					"pivot": [0, 14, 0],
					"cubes": [
						{"origin": [-0.5, 0, -4], "size": [1, 14, 1], "pivot": [0, 14, 0], "rotation": [0, -45, 0], "uv": [78, 53]}
					]
				},
				{
					"name": "rod3",
					"parent": "rods",
					"pivot": [0, 14, 0],
					"cubes": [
						{"origin": [-0.5, 0, -4], "size": [1, 14, 1], "pivot": [0, 14, 0], "rotation": [0, -90, 0], "uv": [78, 53]}
					]
				},
				{
					"name": "rod4",
					"parent": "rods",
					"pivot": [0, 14, 0],
					"cubes": [
						{"origin": [-0.5, 0, -4], "size": [1, 14, 1], "pivot": [0, 14, 0], "rotation": [0, -135, 0], "uv": [78, 53]}
					]
				},
				{
					"name": "rod5",
					"parent": "rods",
					"pivot": [0, 14, 0],
					"cubes": [
						{"origin": [-0.5, 0, -4], "size": [1, 14, 1], "pivot": [0, 14, 0], "rotation": [0, 180, 0], "uv": [78, 53]}
					]
				},
				{
					"name": "rod6",
					"parent": "rods",
					"pivot": [0, 14, 0],
					"cubes": [
						{"origin": [-0.5, 0, -4], "size": [1, 14, 1], "pivot": [0, 14, 0], "rotation": [0, 135, 0], "uv": [78, 53]}
					]
				},
				{
					"name": "rod7",
					"parent": "rods",
					"pivot": [0, 14, 0],
					"cubes": [
						{"origin": [-0.5, 0, -4], "size": [1, 14, 1], "pivot": [0, 14, 0], "rotation": [0, 90, 0], "uv": [78, 53]}
					]
				},
				{
					"name": "rod8",
					"parent": "rods",
					"pivot": [0, 14, 0],
					"cubes": [
						{"origin": [-0.5, 0, -4], "size": [1, 14, 1], "pivot": [0, 14, 0], "rotation": [0, 45, 0], "uv": [78, 53]}
					]
				},
				{
					"name": "body4",
					"parent": "body5",
					"pivot": [0, 22, 0],
					"cubes": [
						{"origin": [-3.5, 22, -3.5], "size": [7, 8, 7], "uv": [44, 16]}
					]
				},
				{
					"name": "body3",
					"parent": "body4",
					"pivot": [0, 30, 0],
					"cubes": [
						{"origin": [-3, 30, -3], "size": [6, 8, 6], "uv": [44, 31]}
					]
				},
				{
					"name": "body2",
					"parent": "body3",
					"pivot": [0, 38, 0],
					"cubes": [
						{"origin": [-4, 38, -4], "size": [8, 8, 8], "uv": [44, 0]}
					]
				},
				{
					"name": "body1",
					"parent": "body2",
					"pivot": [0, 46, 0],
					"cubes": [
						{"origin": [-6, 46, -5], "size": [12, 8, 10], "uv": [0, 18]},
						{"origin": [-2, 53, -2], "size": [4, 4, 4], "uv": [44, 45]},
						{"origin": [-8, 50.5, -1], "size": [16, 2, 2], "uv": [0, 36]}
					]
				},
				{
					"name": "head",
					"parent": "body1",
					"pivot": [0, 57, 0],
					"cubes": [
						{"origin": [-4, 57, -6], "size": [8, 6, 12], "uv": [0, 0]},
						{"origin": [-2, 62, -2], "size": [4, 2, 20], "uv": [76, 0]},
						{"origin": [-5, 62, 0], "size": [2, 2, 12], "uv": [76, 22]},
						{"origin": [-5, 59.5, 0], "size": [2, 2, 8], "uv": [76, 36]},
						{"origin": [-5, 56.5, 3], "size": [2, 2, 5], "uv": [76, 46]},
						{"origin": [-1, 58, 3], "size": [2, 2, 10], "uv": [78, 24]},
						{"origin": [3, 56.5, 3], "size": [2, 2, 5], "uv": [76, 46]},
						{"origin": [3, 59.5, 2], "size": [2, 2, 8], "uv": [76, 36]},
						{"origin": [3, 62, 0], "size": [2, 2, 12], "uv": [76, 22]}
					]
				},
				{
					"name": "left_arm",
					"parent": "body1",
					"pivot": [8, 51.5, 0.5],
					"cubes": [
						{"origin": [8, 39.5, -3], "size": [4, 14, 6], "pivot": [8, 48.5, 0.5], "rotation": [15, 0, 0], "uv": [44, 53]}
					]
				},
				{
					"name": "left_hand",
					"parent": "left_arm",
					"pivot": [10, 40.5, 2],
					"cubes": [
						{"origin": [8.5, 29.5, 0], "size": [3, 12, 4], "pivot": [10, 40.5, 2], "rotation": [-15, 0, 0], "uv": [64, 53]}
					]
				},
				{
					"name": "scythe",
					"parent": "left_hand",
					"pivot": [10, 30, -1],
					"cubes": [
						{"origin": [9, 28, -30], "size": [2, 2, 36], "pivot": [10, 40.5, 2], "rotation": [-15, 0, 0], "uv": [0, 73]},
						{"origin": [8.5, 23, -33], "size": [3, 12, 3], "pivot": [10, 40.5, 2], "rotation": [-15, 0, 0], "uv": [84, 73]},
						{"origin": [9.5, 7, -32.5], "size": [1, 30, 3], "pivot": [10, 40.5, 2], "rotation": [-15, 0, 0], "uv": [76, 73]},
						{"origin": [9.501, 17, -44], "size": [1, 12, 2], "pivot": [10, 40.5, 2], "rotation": [15, 0, 0], "uv": [96, 73]},
						{"origin": [9.5, 36, -49], "size": [1, 8, 1], "pivot": [10, 40.5, 2], "rotation": [45, 0, 0], "uv": [102, 73]}
					]
				},
				{
					"name": "right_arm",
					"parent": "body1",
					"pivot": [-8, 51.5, 0],
					"cubes": [
						{"origin": [-12, 39.5, -3], "size": [4, 14, 6], "pivot": [-8, 48.5, 0.5], "rotation": [15, 0, 0], "uv": [44, 53]}
					]
				},
				{
					"name": "right_hand",
					"parent": "right_arm",
					"pivot": [-10, 40.5, 1],
					"cubes": [
						{"origin": [-11.5, 31, -1], "size": [3, 12, 4], "pivot": [-10, 40.5, 1], "rotation": [-75, 0, 0], "uv": [64, 53]}
					]
				},
				{
					"name": "shield",
					"parent": "right_hand",
					"pivot": [-10, 39, -7],
					"cubes": [
						{"origin": [-14, 24, -8], "size": [20, 30, 2], "pivot": [-10, 40.5, 1], "rotation": [0, 60, 0], "uv": [0, 40]}
					]
				}
			]
		}
	]
}