{
  "affinities": {},
  "manaCost": 10.0,
  "reagents": [],
  "recipe": [
    {
      "type": "arsmagicalegacy:ingredient",
      "count": 1,
      "ingredient": {
        "type": "forge:nbt",
        "count": 1,
        "item": "arsmagicalegacy:affinity_essence",
        "nbt": "{\"arsmagicalegacy:affinity\":\"arsmagicalegacy:fire\"}"
      }
    },
    {
      "type": "arsmagicalegacy:ingredient",
      "count": 1,
      "ingredient": {
        "item": "minecraft:clock"
      }
    },
    {
      "type": "arsmagicalegacy:ingredient",
      "count": 1,
      "ingredient": {
        "item": "arsmagicalegacy:tarma_root"
      }
    },
    {
      "type": "arsmagicalegacy:etherium",
      "amount": 5000,
      "types": [
        "DARK",
        "LIGHT",
        "NEUTRAL"
      ]
    }
  ]
}