{
  "manaCost": 400.0,
  "reagents": [],
  "affinities": {
    "arsmagicalegacy:ender": 0.4
  },
  "recipe": [
    {
      "ingredient": {
        "item": "arsmagicalegacy:purple_rune"
      },
      "count": 1,
      "type": "arsmagicalegacy:ingredient"
    },
    {
      "ingredient": {
        "tag": "forge:ender_pearls"
      },
      "count": 1,
      "type": "arsmagicalegacy:ingredient"
    },
    {
      "ingredient": {
        "item": "minecraft:obsidian"
      },
      "count": 2,
      "type": "arsmagicalegacy:ingredient"
    },
    {
      "ingredient": {
        "type": "forge:nbt",
        "item": "minecraft:flint_and_steel",
        "count": 1,
        "nbt": "{Damage:0}"
      },
      "count": 1,
      "type": "arsmagicalegacy:ingredient"
    }
  ]
}