{
  "type": "forge:conditional",
  "recipes": [
    {
      "conditions": [
        {
          "type": "forge:mod_loaded",
          "modid": "botanypots"
        }
      ],
      "recipe": {
        "type": "botanypots:soil",
        "categories": [
          "stone",
          "mushroom",
          "ore",
          "chimerite_ore",
          "deepslate",
          "deepslate_chimerite_ore"
        ],
        "display": {
          "block": "arsmagicalegacy:deepslate_chimerite_ore"
        },
        "growthModifier": 1.0,
        "input": {
          "item": "arsmagicalegacy:deepslate_chimerite_ore"
        }
      }
    }
  ]
}